CHANGELOG.md
gumby/__init__.py
gumby/cli.py
gumby/core.py
gumby/landmarks.py
gumby/path.py
gumby/recipe.py
gumby-0.6.0.dist-info/LICENSE
gumby-0.6.0.dist-info/WHEEL
gumby-0.6.0.dist-info/METADATA
gumby-0.6.0.dist-info/RECORD
